{
  "_checkout": null,
  "_output_dir": "/Users/tig/coding",
  "_repo_dir": "/Users/tig/.cookiecutters/cookiecutter-uv-hypermodern-python",
  "_template": "gh:bosd/cookiecutter-uv-hypermodern-python",
  "author": "Konstantin Ladutenko",
  "copyright_year": "2025",
  "development_status": "Development Status :: 1 - Planning",
  "email": "kostyfisik@gmail.com",
  "friendly_name": "Np Dist2",
  "github_user": "kostyfisik",
  "license": "MIT",
  "package_name": "np_dist2",
  "project_name": "np-dist2",
  "version": "0.0.0"
}
